src/client.py
message_client_april_2023-0.0.1.dist-info/METADATA
message_client_april_2023-0.0.1.dist-info/WHEEL
message_client_april_2023-0.0.1.dist-info/top_level.txt
message_client_april_2023-0.0.1.dist-info/RECORD
