Metadata-Version: 2.1
Name: message-client-april-2023
Version: 0.0.1
Summary: Client for message server april 2023
Author: Sego
Author-email: grayg@mail.ru
Requires-Dist: PyQt5
Requires-Dist: sqlalchemy
Requires-Dist: pycryptodome
Requires-Dist: pycryptodomex
